Workbook

Sheet STOCK
B2: STOCK GUARDA | H2: APEADOS
B8: REF. | C8: DESCRIPTION | D8: DEP | E8: Sum of QTY | H8: COD | I8: DESCRIÇÃO | J8: QTD
B9: 3000010 | C9: ABRAÇADEIRA INOX 92-97MM | D9: MOVEL | E9: 0 | H9: 3000067 | I9: ALAVANCA | J9: 1
B10: 3000017 | C10: ABRAÇADEIRA METÁLICA INOX 98-103MM | D10: MOVEL | E10: 0 | H10: 3000071 | I10: ALICATE DE CORTE | J10: 1
B11: 3000022 | C11: ABRAÇADEIRA PLÁSTICA 100X2.5MM (PRETA) | D11: FIBRA | E11: 142300 | H11: 3000078 | I11: ALICATE UNIVERSAL | J11: 1
B12: 3000026 | C12: ABRAÇADEIRA PLÁSTICA 2.5X80MM (PRETA) | D12: FIBRA | E12: 82000 | H12: 3000471 | I12: COLHER DE PEDREIRO | J12: 1
B13: 3000035 | C13: ABRAÇADEIRA PLÁSTICA 360X4.8MM (PRETA) | D13: FIBRA | E13: 11090 | H13: 3000480 | I13: CONE DE SINALIZAÇÃO 50CM | J13: 3
B14: 3000067 | C14: ALAVANCA | D14: FERRAMENTA | E14: 1 | H14: 3000535 | I14: DG 206A - 96FO JUNTA FO 8P | J14: 1
B15: 3000068 | C15: ÁLCOOL ISOPROPÍLICO 1LT | D15: FIBRA | E15: 2 | H15: 3000575 | I15: ESCADA 9MT | J15: 3
B16: 3000071 | C16: ALICATE DE CORTE | D16: FERRAMENTA | E16: 6 | H16: 3000586 | I16: EXTENSÃO PARA RACK 19" 9 PORTAS | J16: 2
B17: 3000072 | C17: ALICATE DE CRAVAR RJ11/12/45 | D17: FERRAMENTA | E17: 5 | H17: 3000587 | I17: EXTINTOR 2 KG | J17: 2
B18: 3000073 | C18: ALICATE DESCARNAR FIBRA | D18: FERRAMENTA | E18: 1 | H18: 3000589 | I18: EXTINTOR 6 KG | J18: 4
B19: 3000075 | C19: ALICATE PONTA SEMIREDONDA | D19: FERRAMENTA | E19: 12 | H19: 3000619 | I19: FIXADORES DE ESCADA (SAFE CLAMP) | J19: 4
B20: 3000078 | C20: ALICATE UNIVERSAL | D20: FERRAMENTA | E20: 10 | H20: 3000681 | I20: GANCHO TIPO J (CVP) | J20: 11
... B35: 3000102 | C35: ANEL ALFANUMÉRICO E | D35: FIBRA | E35: 3900 | H35: 3002632 | I35: PATCHCORD SX SM G652D FC/APC - SC/APC 2M | J35: 1
B36: 3000103 | C36: ANEL ALFANUMÉRICO F | D36: FIBRA | E36: 3700 | H36: Grand Total | J36: 86
B37: 3000104 | C37: ANEL ALFANUMÉRICO G | D37: FIBRA | E37: 3500
B38: 3000105 | C38: ANEL ALFANUMÉRICO H | D38: FIBRA | E38: 9300
B39: 3000106 | C39: ANEL ALFANUMÉRICO I | D39: FIBRA | E39: 3400
B40: 3000107 | C40: ANEL ALFANUMÉRICO J | D40: FIBRA | E40: 6400
B41: 3000108 | C41: ANEL ALFANUMÉRICO K | D41: FIBRA | E41: 4300
B42: 3000109 | C42: ANEL ALFANUMÉRICO L | D42: FIBRA | E42: 5900
B43: 3000110 | C43: ANEL ALFANUMÉRICO M | D43: FIBRA | E43: 3900
B44: 3000111 | C44: ANEL ALFANUMÉRICO N | D44: FIBRA | E44: 8900
B45: 3000112 | C45: ANEL ALFANUMÉRICO O | D45: FIBRA | E45: 3900
B46: 3000113 | C46: ANEL ALFANUMÉRICO P | D46: FIBRA | E46: 6400
B47: 3000114 | C47: ANEL ALFANUMÉRICO Q | D47: FIBRA | E47: 6400
B48: 3000115 | C48: ANEL ALFANUMÉRICO R | D48: FIBRA | E48: 6300
... B415: 3003343 | C415: RADIO_2271_(KRC1612208/11)_ERICSSON | D415: MOVEL | E415: 0
B416: 3003455 | C416: CORRENTE PLÁSTICA VERMELHA BRANCA 6MM(25MTS) | D416: 0 | E416: 8
B417: (em branco) | C417: #N/D | D417: #N/D
B418: Total Geral | E418: 882662

Sheet Entradas
A1: CLOG GUARDA
A2: Tipo de Movimento | B2: Dt_Recepção | C2: REF. | D2: DESCRIPTION | E2: QTY | F2: Loc_Inicial | G2: S/N | H2: Lote | I2: Novo Armazém | J2: TRA / DEV | K2: New Localization | L2: Nr Fatura | M2: Nr Albaran | N2: Apeados | O2: DEP | P2: Observações
A3: Alteração de Localização | B3: 46023 | C3: 3000010 | D3: =+VLOOKUP(Table2[[#This Row],[REF.]],Artigos_Primavera!A:B,2,0) -> ABRAÇADEIRA INOX 92-97MM | E3: 4 | F3: GERAL.E | I3: E | K3: GERAL.E | O3: =VLOOKUP(C3,Artigos_Primavera!A:D,4,) -> MOVEL | P3: STOCK 2025
A4: Alteração de Localização | B4: 46023 | C4: 3000017 | D4: =+VLOOKUP(Table2[[#This Row],[REF.]],Artigos_Primavera!A:B,2,0) -> ABRAÇADEIRA METÁLICA INOX 98-103MM | E4: 4 | F4: GERAL.E | I4: E | K4: GERAL.E | O4: =VLOOKUP(C4,Artigos_Primavera!A:D,4,) -> MOVEL | P4: STOCK 2025
A5: Alteração de Localização | B5: 46023 | C5: 3000022 | D5: =+VLOOKUP(Table2[[#This Row],[REF.]],Artigos_Primavera!A:B,2,0) -> ABRAÇADEIRA PLÁSTICA 100X2.5MM (PRETA) | E5: 146600 | F5: GERAL.E | I5: E | K5: GERAL.E | O5: =VLOOKUP(C5,Artigos_Primavera!A:D,4,) -> FIBRA | P5: STOCK 2025
A6: Alteração de Localização | B6: 46023 | C6: 3000026 | D6: =+VLOOKUP(Table2[[#This Row],[REF.]],Artigos_Primavera!A:B,2,0) -> ABRAÇADEIRA PLÁSTICA 2.5X80MM (PRETA) | E6: 82000 | F6: GERAL.E | I6: E | K6: GERAL.E | O6: =VLOOKUP(C6,Artigos_Primavera!A:D,4,) -> FIBRA | P6: STOCK 2025
A7: Alteração de Localização | B7: 46023 | C7: 3000035 | D7: =+VLOOKUP(Table2[[#This Row],[REF.]],Artigos_Primavera!A:B,2,0) -> ABRAÇADEIRA PLÁSTICA 360X4.8MM (PRETA) | E7: 16800 | F7: GERAL.E | I7: E | K7: GERAL.E | O7: =VLOOKUP(C7,Artigos_Primavera!A:D,4,) -> FIBRA | P7: STOCK 2025
A8: Alteração de Localização | B8: 46023 | C8: 3000067 | D8: =+VLOOKUP(Table2[[#This Row],[REF.]],Artigos_Primavera!A:B,2,0) -> ALAVANCA | E8: 2 | F8: GERAL.E | I8: E | K8: GERAL.E | O8: =VLOOKUP(C8,Artigos_Primavera!A:D,4,) -> FERRAMENTA | P8: STOCK 2025
A9: Alteração de Localização | B9: 46023 | C9: 3000068 | D9: =+VLOOKUP(Table2[[#This Row],[REF.]],Artigos_Primavera!A:B,2,0) -> ÁLCOOL ISOPROPÍLICO 1LT | E9: 6 | F9: GERAL.E | I9: E | K9: GERAL.E | O9: =VLOOKUP(C9,Artigos_Primavera!A:D,4,) -> FIBRA | P9: STOCK 2025
A10: Alteração de Localização | B10: 46023 | C10: 3000071 | D10: =+VLOOKUP(Table2[[#This Row],[REF.]],Artigos_Primavera!A:B,2,0) -> ALICATE DE CORTE | E10: 8 | F10: GERAL.E | I10: E | K10: GERAL.E | O10: =VLOOKUP(C10,Artigos_Primavera!A:D,4,) -> FERRAMENTA | P10: STOCK 2025
A11: Alteração de Localização | B11: 46023 | C11: 3000073 | D11: =+VLOOKUP(Table2[[#This Row],[REF.]],Artigos_Primavera!A:B,2,0) -> ALICATE DESCARNAR FIBRA | E11: 2 | F11: GERAL.E | I11: E | K11: GERAL.E | O11: =VLOOKUP(C11,Artigos_Primavera!A:D,4,) -> FERRAMENTA | P11: STOCK 2025
A12: Alteração de Localização | B12: 46023 | C12: 3000075 | D12: =+VLOOKUP(Table2[[#This Row],[REF.]],Artigos_Primavera!A:B,2,0) -> ALICATE PONTA SEMIREDONDA | E12: 13 | F12: GERAL.E | I12: E | K12: GERAL.E | O12: =VLOOKUP(C12,Artigos_Primavera!A:D,4,) -> FERRAMENTA | P12: STOCK 2025
A13: Alteração de Localização | B13: 46023 | C13: 3000078 | D13: =+VLOOKUP(Table2[[#This Row],[REF.]],Artigos_Primavera!A:B,2,0) -> ALICATE UNIVERSAL | E13: 10 | F13: GERAL.E | I13: E | K13: GERAL.E | O13: =VLOOKUP(C13,Artigos_Primavera!A:D,4,) -> FERRAMENTA | P13: STOCK 2025
D14: =+VLOOKUP(Table2[[#This Row],[REF.]],Artigos_Primavera!A:B,2,0) -> #N/A | O14: =VLOOKUP(C14,Artigos_Primavera!A:D,4,) -> #N/A
D15: =+VLOOKUP(Table2[[#This Row],[REF.]],Artigos_Primavera!A:B,2,0) -> #N/A | O15: =VLOOKUP(C15,Artigos_Primavera!A:D,4,) -> #N/A
D16: =+VLOOKUP(Table2[[#This Row],[REF.]],Artigos_Primavera!A:B,2,0) -> #N/A | O16: =VLOOKUP(C16,Artigos_Primavera!A:D,4,) -> #N/A
D17: =+VLOOKUP(Table2[[#This Row],[REF.]],Artigos_Primavera!A:B,2,0) -> #N/A | O17: =VLOOKUP(C17,Artigos_Primavera!A:D,4,) -> #N/A
D18: =+VLOOKUP(Table2[[#This Row],[REF.]],Artigos_Primavera!A:B,2,0) -> #N/A | O18: =VLOOKUP(C18,Artigos_Primavera!A:D,4,) -> #N/A
D19: =+VLOOKUP(Table2[[#This Row],[REF.]],Artigos_Primavera!A:B,2,0) -> #N/A | O19: =VLOOKUP(C19,Artigos_Primavera!A:D,4,) -> #N/A
D20: =+VLOOKUP(Table2[[#This Row],[REF.]],Artigos_Primavera!A:B,2,0) -> #N/A | O20: =VLOOKUP(C20,Artigos_Primavera!A:D,4,) -> #N/A
D21: =+VLOOKUP(Table2[[#This Row],[REF.]],Artigos_Primavera!A:B,2,0) -> #N/A | O21: =VLOOKUP(C21,Artigos_Primavera!A:D,4,) -> #N/A
D22: =+VLOOKUP(Table2[[#This Row],[REF.]],Artigos_Primavera!A:B,2,0) -> #N/A | O22: =VLOOKUP(C22,Artigos_Primavera!A:D,4,) -> #N/A
D23: =+VLOOKUP(Table2[[#This Row],[REF.]],Artigos_Primavera!A:B,2,0) -> #N/A | O23: =VLOOKUP(C23,Artigos_Primavera!A:D,4,) -> #N/A
D24: =+VLOOKUP(Table2[[#This Row],[REF.]],Artigos_Primavera!A:B,2,0) -> #N/A | O24: =VLOOKUP(C24,Artigos_Primavera!A:D,4,) -> #N/A

Sheet APEADOS
A1: Tipo de Movimento | B1: Dt_Recepção | C1: REF. | D1: DESCRIPTION | E1: QTY | F1: Loc_Inicial | G1: S/N | H1: Lote | I1: Observações | J1: Novo Armazém | K1: TRA / DEV | L1: New Localization | M1: Nr Fatura | N1: Nr Albaran | O1: Apeados | P1: DEP
A2: TRA APEADOS | B2: 46023 | C2: 3000067 | D2: =+VLOOKUP(Table28[[#This Row],[REF.]],Artigos_Primavera!A:B,2,0) -> ALAVANCA | E2: 3 | F2: E | I2: STOCK 2025 | J2: APE.E | P2: =VLOOKUP(C2, Artigos_Primavera!A:D, 4, FALSE) -> FERRAMENTA
A3: TRA APEADOS | B3: 46023 | C3: 3000071 | D3: =+VLOOKUP(Table28[[#This Row],[REF.]],Artigos_Primavera!A:B,2,0) -> ALICATE DE CORTE | E3: 1 | F3: E | I3: STOCK 2025 | J3: APE.E | P3: =VLOOKUP(C3, Artigos_Primavera!A:D, 4, FALSE) -> FERRAMENTA
A4: TRA APEADOS | B4: 46023 | C4: 3000078 | D4: =+VLOOKUP(Table28[[#This Row],[REF.]],Artigos_Primavera!A:B,2,0) -> ALICATE UNIVERSAL | E4: 1 | F4: E | I4: STOCK 2025 | J4: APE.E | P4: =VLOOKUP(C4, Artigos_Primavera!A:D, 4, FALSE) -> FERRAMENTA
A5: TRA APEADOS | B5: 46023 | C5: 3000480 | D5: =+VLOOKUP(Table28[[#This Row],[REF.]],Artigos_Primavera!A:B,2,0) -> CONE DE SINALIZAÇÃO 50CM | E5: 1 | F5: E | I5: STOCK 2025 | J5: APE.E | P5: =VLOOKUP(C5, Artigos_Primavera!A:D, 4, FALSE) -> EPC
A6: TRA APEADOS | B6: 46023 | C6: 3000535 | D6: =+VLOOKUP(Table28[[#This Row],[REF.]],Artigos_Primavera!A:B,2,0) -> DG 206A - 96FO JUNTA FO 8P | E6: 1 | F6: E | I6: STOCK 2025 | J6: APE.E | P6: =VLOOKUP(C6, Artigos_Primavera!A:D, 4, FALSE) -> FIBRA
A7: TRA APEADOS | B7: 46023 | C7: 3000575 | D7: =+VLOOKUP(Table28[[#This Row],[REF.]],Artigos_Primavera!A:B,2,0) -> ESCADA 9MT | E7: 2 | F7: E | I7: STOCK 2025 | J7: APE.E | P7: =VLOOKUP(C7, Artigos_Primavera!A:D, 4, FALSE) -> FERRAMENTA
A8: TRA APEADOS | B8: 46023 | C8: 3000586 | D8: =+VLOOKUP(Table28[[#This Row],[REF.]],Artigos_Primavera!A:B,2,0) -> EXTENSÃO PARA RACK 19" 9 PORTAS | E8: 2 | F8: E | I8: STOCK 2025 | J8: APE.E | P8: =VLOOKUP(C8, Artigos_Primavera!A:D, 4, FALSE) -> MOVEL
A9: TRA APEADOS | B9: 46023 | C9: 3000587 | D9: =+VLOOKUP(Table28[[#This Row],[REF.]],Artigos_Primavera!A:B,2,0) -> EXTINTOR 2 KG | E9: 2 | F9: E | I9: STOCK 2025 | J9: APE.E | P9: =VLOOKUP(C9, Artigos_Primavera!A:D, 4, FALSE) -> EPC
A10: TRA APEADOS | B10: 46023 | C10: 3000589 | D10: =+VLOOKUP(Table28[[#This Row],[REF.]],Artigos_Primavera!A:B,2,0) -> EXTINTOR 6 KG | E10: 4 | F10: E | I10: STOCK 2025 | J10: APE.E | P10: =VLOOKUP(C10, Artigos_Primavera!A:D, 4, FALSE) -> EPC
A11: TRA APEADOS | B11: 46023 | C11: 3000619 | D11: =+VLOOKUP(Table28[[#This Row],[REF.]],Artigos_Primavera!A:B,2,0) -> FIXADORES DE ESCADA (SAFE CLAMP) | E11: 2 | F11: E | I11: STOCK 2025 | J11: APE.E | P11: =VLOOKUP(C11, Artigos_Primavera!A:D, 4, FALSE) -> FERRAMENTA
A12: TRA APEADOS | B12: 46023 | C12: 3000681 | D12: =+VLOOKUP(Table28[[#This Row],[REF.]],Artigos_Primavera!A:B,2,0) -> GANCHO TIPO J (CVP) | E12: 9 | F12: E | I12: STOCK 2025 | J12: APE.E | P12: =VLOOKUP(C12, Artigos_Primavera!A:D, 4, FALSE) -> FERRAMENTA
A13: TRA APEADOS | B13: 46023 | C13: 3000682 | D13: =+VLOOKUP(Table28[[#This Row],[REF.]],Artigos_Primavera!A:B,2,0) -> GANCHO TIPO T (CVP) | E13: 8 | F13: E | I13: STOCK 2025 | J13: APE.E | P13: =VLOOKUP(C13, Artigos_Primavera!A:D, 4, FALSE) -> FERRAMENTA
... A26: TRA APEADOS | B26: 46023 | C26: 3002632 | D26: =+VLOOKUP(Table28[[#This Row],[REF.]],Artigos_Primavera!A:B,2,0) -> PATCHCORD SX SM G652D FC/APC - SC/APC 2M | E26: 1 | F26: E | I26: STOCK 2025 | J26: APE.E | P26: =VLOOKUP(C26, Artigos_Primavera!A:D, 4, FALSE) -> FIBRA
A27: TRA APEADOS | B27: 46027 | C27: 3000480 | D27: =+VLOOKUP(Table28[[#This Row],[REF.]],Artigos_Primavera!A:B,2,0) -> CONE DE SINALIZAÇÃO 50CM | E27: 2 | F27: E | J27: APE.E | K27: TRA 34/2026 | P27: =VLOOKUP(C27, Artigos_Primavera!A:D, 4, FALSE) -> EPC
A28: TRA APEADOS | B28: 46029 | C28: 3001397 | D28: =+VLOOKUP(Table28[[#This Row],[REF.]],Artigos_Primavera!A:B,2,0) -> X-ACTO | E28: 1 | F28: E | J28: APE.E | K28: TRA 77/2026 | P28: =VLOOKUP(C28, Artigos_Primavera!A:D, 4, FALSE) -> FERRAMENTA
A29: TRA APEADOS | B29: 46029 | C29: 3001961 | D29: =+VLOOKUP(Table28[[#This Row],[REF.]],Artigos_Primavera!A:B,2,0) -> POWER METER GPON TL-520A | E29: 1 | F29: E | G29: 210814-09 | J29: APE.E | K29: TRA 77/2026 | P29: =VLOOKUP(C29, Artigos_Primavera!A:D, 4, FALSE) -> FERRAMENTA
A30: TRA APEADOS | B30: 46029 | C30: 3001961 | D30: =+VLOOKUP(Table28[[#This Row],[REF.]],Artigos_Primavera!A:B,2,0) -> POWER METER GPON TL-520A | E30: 1 | F30: E | G30: 210814128 | J30: APE.E | K30: TRA 77/2026 | P30: =VLOOKUP(C30, Artigos_Primavera!A:D, 4, FALSE) -> FERRAMENTA
A31: TRA APEADOS | B31: 46030 | C31: 3000067 | D31: =+VLOOKUP(Table28[[#This Row],[REF.]],Artigos_Primavera!A:B,2,0) -> ALAVANCA | E31: -2 | F31: APE.E | J31: E | K31: TRA 136/2026 | L31: GERAL.E | P31: =VLOOKUP(C31, Artigos_Primavera!A:D, 4, FALSE) -> FERRAMENTA
A32: TRA APEADOS | B32: 46034 | C32: 3001961 | D32: =+VLOOKUP(Table28[[#This Row],[REF.]],Artigos_Primavera!A:B,2,0) -> POWER METER GPON TL-520A | E32: -1 | F32: APE.E | G32: 210814-09 | J32: E | K32: TRA 213/2026 | L32: GERAL.E | P32: =VLOOKUP(C32, Artigos_Primavera!A:D, 4, FALSE) -> FERRAMENTA
A33: TRA APEADOS | B33: 46038 | C33: 3000575 | D33: =+VLOOKUP(Table28[[#This Row],[REF.]],Artigos_Primavera!A:B,2,0) -> ESCADA 9MT | E33: 1 | F33: E | G33: PT0106 | J33: APE.E | K33: TRA 343/2026 | P33: =VLOOKUP(C33, Artigos_Primavera!A:D, 4, FALSE) -> FERRAMENTA
A34: TRA APEADOS | B34: 46038 | C34: 3000471 | D34: =+VLOOKUP(Table28[[#This Row],[REF.]],Artigos_Primavera!A:B,2,0) -> COLHER DE PEDREIRO | E34: 1 | F34: E | J34: APE.E | K34: TRA 343/2026 | P34: =VLOOKUP(C34, Artigos_Primavera!A:D, 4, FALSE) -> FERRAMENTA
A35: TRA APEADOS | B35: 46049 | C35: 3000681 | D35: =+VLOOKUP(Table28[[#This Row],[REF.]],Artigos_Primavera!A:B,2,0) -> GANCHO TIPO J (CVP) | E35: 2 | F35: ZEXT.E | J35: APE.E | K35: TRA 578/2026 | P35: =VLOOKUP(C35, Artigos_Primavera!A:D, 4, FALSE) -> FERRAMENTA
A36: TRA APEADOS | B36: 46049 | C36: 3001397 | D36: =+VLOOKUP(Table28[[#This Row],[REF.]],Artigos_Primavera!A:B,2,0) -> X-ACTO | E36: 1 | F36: ZEXT.E | J36: APE.E | K36: TRA 578/2026 | P36: =VLOOKUP(C36, Artigos_Primavera!A:D, 4, FALSE) -> FERRAMENTA
A37: TRA APEADOS | B37: 46049 | C37: 3002454 | D37: =+VLOOKUP(Table28[[#This Row],[REF.]],Artigos_Primavera!A:B,2,0) -> BARREIRA EXTENSÍVEL | E37: 1 | F37: ZEXT.E | J37: APE.E | K37: TRA 578/2026 | P37: =VLOOKUP(C37, Artigos_Primavera!A:D, 4, FALSE) -> EPC
A38: TRA APEADOS | B38: 46051 | C38: 3001047 | D38: =+VLOOKUP(Table28[[#This Row],[REF.]],Artigos_Primavera!A:B,2,0) -> PÉ DE CABRA | E38: 1 | F38: E | J38: APE.E | K38: DEV 70/2026 | P38: =VLOOKUP(C38, Artigos_Primavera!A:D, 4, FALSE) -> FERRAMENTA
A39: TRA APEADOS | B39: 46058 | C39: 3000619 | D39: FIXADORES DE ESCADA (SAFE CLAMP) | E39: 1 | F39: E | J39: APE.E | K39: TRA 781/2026 | P39: =VLOOKUP(C39, Artigos_Primavera!A:D, 4, FALSE) -> FERRAMENTA
A40: TRA APEADOS | B40: 46059 | C40: 3000619 | D40: =+VLOOKUP(Table28[[#This Row],[REF.]],Artigos_Primavera!A:B,2,0) -> FIXADORES DE ESCADA (SAFE CLAMP) | E40: 1 | F40: E | J40: APE.E | K40: TRA 798/2026 | P40: =VLOOKUP(C40, Artigos_Primavera!A:D, 4, FALSE) -> FERRAMENTA
A41: TRA APEADOS | B41: 46062 | C41: 3001397 | D41: =+VLOOKUP(Table28[[#This Row],[REF.]],Artigos_Primavera!A:B,2,0) -> X-ACTO | E41: 1 | F41: E | J41: APE.E | K41: TRA 814/2026 | P41: =VLOOKUP(C41, Artigos_Primavera!A:D, 4, FALSE) -> FERRAMENTA

Sheet Artigos_Primavera
A1: Artigo | B1: Descrição (Artigo) | C1: Unidade Base | D1: DEP
A2: 1100 MW EXPANSION SUPPORT 2024 PO04 | B2: 1100 MW EXPANSION SUPPORT 2024 PO04 | C2: UN | D2: FIBRA
A3: 12 MW EXPANSION SUPPORT 2024 PO05 | B3: 12 MW EXPANSION SUPPORT 2024 PO05 | C3: UN | D3: FIBRA
A4: 1325 | B4: Fibra SMART 1Gb | C4: UN | D4: FIBRA
A5: 1432 | B5: Combo (100 GB + 800 min) | C5: UN | D5: FIBRA
A6: 1440 | B6: Combo (100 GB + 800 min) | C6: UN | D6: FIBRA
A7: 1465 | B7: DIGI TV | C7: UN | D7: FIBRA
A8: 1466 | B8: DIGI TV | C8: UN | D8: FIBRA
A9: 1502 | B9: Móvel 50 GB | C9: UN | D9: FIBRA
A10: 1503 | B10: Móvel 100 GB | C10: UN | D10: FIBRA
A11: 1504 | B11: Móvel 150 GB | C11: UN | D11: FIBRA
A12: 1505 | B12: Móvel ILIMITADO | C12: UN | D12: FIBRA
A13: 1506 | B13: Móvel ILIMITADO | C13: UN | D13: FIBRA
A14: 1507 | B14: Móvel ILIMITADO | C14: UN | D14: FIBRA
A15: 1508 | B15: Móvel 200 GB | C15: UN | D15: FIBRA
... A2891: 3002907 | B2891: SERVER AS 2124US TNRP SUPERMICRO | C2891: UN | D2891: FIBRA
A2892: 3002908 | B2892: MANUAL ONT OPTIXSTAR HG8147X6-10 GPON - HUAWEI | C2892: UN
A2893: 3002909 | B2893: SINAL PERIGO EMPILHADORES EM CIRCULAÇÃO | C2893: UN
A2894: 3002910 | B2894: HPE C13/C14 WW 10A 1.4m Blk 6pc | C2894: UN
A2895: 3002911 | B2895: HPE DL360Gen10+ Standard ICX CX6 | C2895: UN
A2896: 3002912 | B2896: FITA ISOLADORA LARANJA | C2896: UN
A2897: 3002913 | B2897: TESOURA CORTE FERRO | C2897: UN | D2897: FERRAMENTA
A2898: 3002914 | B2898: POWER DISTRIBUTION UNIT ADPD2-A NOKIA | C2898: UN
A2899: 3002915 | B2899: ENVELOPE LOGO DIGI C/JANELA TAM. DL | C2899: UN
A2900: 3002916 | B2900: CABO ELÉTRICO ANTI-FOGO RZ1 - K(AS) 1KV 5G10 | C2900: MT
A2901: 3002917 | B2901: SURSA FLATPACK D - 48V 12KW 3S400V+N BD LD | C2901: UN
A2902: 3002918 | B2902: MODULO RETIFICADOR FLATPACK D - 48/3000 SHE+ | C2902: UN
A2903: 3002919 | B2903: TONER BROTHER PRETO XL TN821XLBK | C2903: UN
A2904: 3002920 | B2904: TONER BROTHER CYAN XL TN821XLC | C2904: UN
A2905: 3002921 | B2905: TONER BROTHER AMARELO XL TN821XLY | C2905: UN
A2906: 3002922 | B2906: TONER BROTHER MAGENTA XL TN821XLM | C2906: UN
A2907: 3002923 | B2907: SURSA FLATPACK D - 48V 12KW 3S400V+N BD LD | C2907: UN
A2908: 3002924 | B2908: MODULO RETIFICADOR FLATPACK D - 48/3000 SHE+ | C2908: UN
A2909: 3002926 | B2909: PATCHCORD SC/APC - SC/APC SM 3.0MM WHITE 6MT | C2909: UN
... A2940: 3002957 | B2940: PAINEL ESPUMA ABSORVENTE ACUSTICO IGNIFUGO | C2940: UN
A2941: 3002958 | B2941: MANUAL ONT GPON ZTE ZXHN F601C | C2941: UN | D2941: REDE CLIENTE
A2942: 3002959 | B2942: TALHA CARDENAL 25 MT | C2942: UN | D2942: FERRAMENTA
A2943: 3002960 | B2943: PATCHCORD SM G657A2 2mm LC/PC LC/PC 5 MT | C2943: UN
A2944: 3002961 | B2944: VINIL NOVO LOGO STAND MOVEL (MK) | C2944: UN
A2945: 3002962 | B2945: LÂMINA CLIVER FUJIKURA | C2945: UN
A2946: 3002963 | B2946: CAIXA DERIVAÇÃO 80X80X45 | C2946: UN
A2947: 3002964 | B2947: CALHA 20X12,5 ADESIVA BRANCA | C2947: MT
A2948: 3002965 | B2948: LIGADOR 2 CONDUTORES (UY2) 0,4 - 0,9 MM2 | C2948: UN
A2949: 3002966 | B2949: CALHA 110X50 BRANCA | C2949: MT
A2950: 3002967 | B2950: COLA DE CONTACTO SPRAY | C2950: UN
A2951: 3002968 | B2951: CONECTOR RF_COUPLER 698-2700MHZ XMCP06N5001_HILINKS 6DB | C2951: UN
A2952: 3002969 | B2952: CONECTOR RF_COUPLER 698-2700MHZ XMCP10N5001_HILINKS 10DB | C2952: UN
A2953: 3002970 | B2953: CONECTOR RF_COUPLER 698-2700MHZ XMCP15N5001_HILINKS 15DB | C2953: UN
A2954: 3002971 | B2954: VINIL FACHADA XL (MK) | C2954: UN
... A2958: 3002975 | B2958: DIPTICO DROPMAIL MAI 25 (MK) | C2958: UN
A2959: 3002976 | B2959: TRIPTICO JUN 25 (MK) | C2959: UN | D2959: MKT
A2960: 3002977 | B2960: DIPTICO JUN 25 (MK) | C2960: UN
A2961: 3002978 | B2961: CART TINT HP 712 DJ T200/T600 29ML AML | C2961: UN
A2962: 3002979 | B2962: CART TINT HP 712 DJ T200/T600 29ML CYA | C2962: UN
A2963: 3002980 | B2963: CART TINT HP 712 DJ T200/T600 29ML MGT | C2963: UN
A2964: 3002981 | B2964: TONER LSR BROTHER TN-248M 1K MGT | C2964: UN
A2965: 3002982 | B2965: TONER LSR BROTHER TN-248BK 1K NGO | C2965: UN
A2966: 3002983 | B2966: TONER LSR BROTHER TN-248C 1K CIA | C2966: UN
A2967: 3002984 | B2967: CART TINT HP 712 DJ T200/T600 38ML PTO | C2967: UN
A2968: 3002985 | B2968: TONER LSR BROTHER 248XL 2.3K AML | C2968: UN
A2969: 3002986 | B2969: SPRAY AR COMPRIMIDO | C2969: UN
A2970: 3002987 | B2970: AGRAFADOR INDUSTRIAL | C2970: UN
A2971: 3002988 | B2971: CANETA ESCREVER ROSA | C2971: CX
... A2999: 3003016 | B2999: BOLSA PLASTIFICAÇÃO A4 | C2999: EMB
A3000: 3003017 | B3000: SAPATO S3 TAM 43 | C3000: UN | D3000: EPI
A3001: 3003018 | B3001: BUCHA DE FIXAÇÃO M12X200MM | C3001: UN
A3002: 3003019 | B3002: BUCHA DE FIXAÇÃO M10X145MM | C3002: UN
A3003: 3003020 | B3003: BUCHA DE FIXAÇÃO M12X285MM | C3003: UN
A3004: 3003021 | B3004: ANTENA_INDOOR BIDIR 65GRD 9012 1LM (KRE 101 2572/1)_ERICSSON | C3004: UN
A3005: 3003022 | B3005: ARMÁRIO ELÉTRICO 3X400V 40A RELIGADOR | C3005: UN
A3006: 3003023 | B3006: TAPETE DE BORRACHA 10X1200MM | C3006: MT
A3007: 3003024 | B3007: ON325313 - OTP40_PLR4 | C3007: UN
A3008: 3003025 | B3008: ON328278 - OTR400P2_CFA2 | C3008: UN
A3009: 3003026 | B3009: ON328451 - OTR200P2_CFA2 | C3009: UN
A3010: 3003027 | B3010: X44432 - SP_CE8_1 | C3010: UN
A3011: 3003028 | B3011: X44779 - C_OTDR_2 | C3011: UN
A3012: 3003029 | B3012: X57609 - PFM03_H | C3012: UN
... A3078: 3003096 | B3078: PELICULA NOBO C/25FLS X 80X60CM | C3078: UN
A3079: 3003097 | B3079: BROCA SDS 12MM 365X460MM | C3079: UN | D3079: FERRAMENTA
A3080: 3003098 | B3080: BROCA SDS 18MM 365X460MM | C3080: UN | D3080: FERRAMENTA
A3081: 3003100 | B3081: PONTEIRA FACA CONECTOR 23x4x10MMP | C3081: UN
A3082: 3003101 | B3082: PONTEIRA FACA CONECTOR 19.1X2.9X6MMP | C3082: UN | D3082: MOVEL
A3083: 3003102 | B3083: BERBEQUIM PERCUSSÃO | C3083: UN | D3083: FERRAMENTA
A3084: 3003103 | B3084: REBARBADORA ANGULAR KRESS | C3084: UN | D3084: FERRAMENTA
A3085: 3003104 | B3085: APARAFUSADORA HIKOKI 18V | C3085: UN | D3085: FERRAMENTA
A3086: 3003105 | B3086: CHAVE PHILIPS 0-60 | C3086: UN | D3086: FERRAMENTA
A3087: 3003106 | B3087: JOGO DE CATRACA 41 PEÇAS | C3087: UN | D3087: FERRAMENTA
A3088: 3003107 | B3088: ALICATE PONTA REDONDA | C3088: UN | D3088: FERRAMENTA
A3089: 3003108 | B3089: CAMINHO CABOS CHAPA 60X100 3M | C3089: UN
A3090: 3003109 | B3090: PERFIL TIPO C PERFURADO 2M | C3090: UN
A3091: 3003110 | B3091: VARÃO ROSCADO M6 | C3091: UN
A3092: 3003111 | B3092: KIT UNIÃO PEMSABAND M6X12 | C3092: UN
A3093: 3003112 | B3093: BUCHA METÁLICA M06X45 | C3093: UN
A3094: 3003113 | B3094: UNIÃO P/TUBO VD 40 | C3094: UN
A3095: 3003114 | B3095: CURVA P/TUBO VD 40 902 | C3095: UN
A3096: 3003115 | B3096: CABO TERRA 50MM (AMARELO/VERDE) | C3096: MT
A3097: 3003116 | B3097: CABO COBRE 50MM | C3097: MT
A3098: 3003117 | B3098: ELECTRODO TERRA 5/8" 2M | C3098: UN
A3099: 3003118 | B3099: CAMISA BRANCA LOGO DIGI MANGA COMPRIDA TAM. M ( MK ) | C3099: UN | D3099: EPI
A3100: 3003119 | B3100: CAMISA BRANCA LOGO DIGI MANGA COMPRIDA TAM. XL ( MK ) | C3100: UN | D3100: EPI
...

Sheet 051023_Lista Artigos Geral
A1: OLD ARTICLE | B1: OLD DESCRIPTION | C1: NEW ARTICLE | D1: NEW DESCRIPTION | E1: OLD ARTICLE | F1: OLD DESCRIPTION
A2: MOB0010659 | B2: 10/100/1000BASE-T SFP HI | C2: 3000000 | D2: 10/100/1000BASE-T SFP HI | E2: MOB0010659 | F2: 10/100/1000BASE-T SFP HI
A3: MOB0010581 | B3: 10G SWITCH | C3: 3000001 | D3: 10G SWITCH | E3: MOB0010581 | F3: 10G SWITCH
A4: MOB0010717 | B4: 121-20621-11-2 SFP MODUL | C4: 3000002 | D4: 121-20621-11-2 SFP MODUL | E4: MOB0010717 | F4: 121-20621-11-2 SFP MODUL
A5: MOB0010254 | B5: ABIA AirScale Capacity Remanufactured | C5: 3000003 | D5: ABIA AIRSCALE CAPACITY REMANUFACTURED | E5: MOB0010254 | F5: ABIA AirScale Capacity Remanufactured
A6: MOB0010265 | B6: ABIO AirScale Capacity | C6: 3000004 | D6: ABIO AIRSCALE CAPACITY | E6: MOB0010265 | F6: ABIO AirScale Capacity
A7: GER0010189 | B7: ABRAÇADEIRA | C7: 3000005 | D7: ABRAÇADEIRA | E7: GER0010189 | F7: ABRAÇADEIRA
A8: MOB0010145 | B8: ABRAÇADEIRA INOX 100-120MM | C8: 3000006 | D8: ABRAÇADEIRA INOX 100-120MM | E8: MOB0010145 | F8: ABRAÇADEIRA INOX 100-120MM
A9: MOB0010146 | B9: ABRAÇADEIRA INOX 110-130MM | C9: 3000007 | D9: ABRAÇADEIRA INOX 110-130MM | E9: MOB0010146 | F9: ABRAÇADEIRA INOX 110-130MM
A10: MOB0010153 | B10: ABRAÇADEIRA INOX 60-80MM | C10: 3000008 | D10: ABRAÇADEIRA INOX 60-80MM | E10: MOB0010153 | F10: ABRAÇADEIRA INOX 60-80MM
A11: MOB0010147 | B11: ABRAÇADEIRA INOX 70-90MM | C11: 3000009 | D11: ABRAÇADEIRA INOX 70-90MM | E11: MOB0010147 | F11: ABRAÇADEIRA INOX 70-90MM
A12: MOB0010173 | B12: ABRAÇADEIRA INOX 92-97MM | C12: 3000010 | D12: ABRAÇADEIRA INOX 92-97MM | E12: MOB0010173 | F12: ABRAÇADEIRA INOX 92-97MM
A13: MOB0010157 | B13: ABRAÇADEIRA M12 P/ TUBO Ø121 C/ 130MM 8.8 GALVAN | C13: 3000011 | D13: ABRAÇADEIRA M12 P/ TUBO Ø121 C/ 130MM 8.8 GALVAN | E13: MOB0010157 | F13: ABRAÇADEIRA M12 P/ TUBO Ø121 C/ 130MM 8.8 GALVAN
... A1407: N/A | B1407: N/A | C1407: 3001463 | D1407: PATCHCORD SC/APC - SC/APC 6MT | E1407: N/A | F1407: N/A

Sheet Localização Destino
A1: Carrinha
A2: Devolução Armazém A
A3: Digi Porto
A4: Ruben Carapinha

Sheet Pivot
A5: Sum of QtY
A6: 344964

Sheet Artgs Stefan
A1: NEW ARTICLE | B1: NEW DESCRIPTION | C1: OLD ARTICLE | D1: OLD DESCRIPTION | E1: Tipo
A2: 3000534 | B2: DG 206 - 288FO JUNTA OPTICA | C2: FIB0020002 | D2: DG 206 - 288 FO Junta Optica YS-GPJ-801-6P 6TRY | E2: Juntas
A3: 3000535 | B3: DG 206A - 96FO JUNTA FO 8P | C3: FIB0020001 | D3: DG 206A Junta FO Optica YS-GPJ-801/8P 96FO | E3: Juntas
A4: 3000801 | B4: JUNTA FIBRA OPTICA 512FO | C4: FIB0020003 | D4: Junta Fibra Optica 512FO | E4: Juntas
A5: 3001044 | B5: PDO 8P | C5: FIB0020005 | D5: PDO DG.002.8P | E5: PDO
A6: 3001045 | B6: PDO HTSC-203 BLACK | C6: FIB0020004 | D6: PDO HTSC-203 BLACK | E6: PDO
A7: 3001041 | B7: PDO 18P | C7: FIB0030001 | D7: PDO DG.001.18P | E7: PDO
A8: 3001043 | B8: PDO 48P | C8: FIB0030004 | D8: PDO DG-003 48P, 6 Bandejas, 24 Adaptadores | E8: PDO
A9: 3001042 | B9: PDO 32P | C9: FIB0030005 | D9: PDO DG-003 Mini, 32P, 4 Bandejas, 16 Adaptadores | E9: PDO
A10: 3001251 | B10: SPLITTER 1X12. SEM CONECTOR | C10: FIB0040014 | D10: Splitter 1x12 IN, 1m/OUT 1m, SEM Conector | E10: Splitters
A11: 3001250 | B11: SPLITTER 1X12. COM CONECTOR SC/APC | C11: FIB0040024 | D11: Splitter 1x12, IN 1,5m / OUT 1m C/conector SC/APC | E11: Splitters
A12: 3001252 | B12: SPLITTER 1X16. COM CONECTOR SC/APC | C12: FIB0040026 | D12: Splitter 1x16 IN 1,5m/OUT 1m, C/conector SC/APC | E12: Splitters
A13: 3001253 | B13: SPLITTER 1X16. SEM CONECTOR | C13: FIB0040025 | D13: Splitter 1x16 IN 1m/OUT 1m, SEM Conector | E13: Splitters
... A35: 3001294 | B35: SUPORTE JUNTA DG.206 | C35: FIB0050115 | D35: Suporte Junta DG.206 | E35: Suporte Juntas

Sheet Tipo Movimento
A1: Saída de Armazém
A2: Devolução de Carrinha
A3: TRA ARM. A
A4: Entrada de Fornecedor
A5: Alteração de Localização
A6: Alteração de Armazém
A7: Devolução de EPI'S/EPC
A8: Devolução ao armazém A
A9: Transf entre Deptos
A10: TRA APEADOS

Sheet Armazéns
A1: Descrição | B1: Armazém | C1: Descrição2
A2: Armazém Cacém | B2: A | C2: Armazém Cacém
A3: Armazém Porto | B3: B | C3: Armazém Porto
A4: Armazém Leiria | B4: C | C4: Armazém Leiria
A5: Setling | B5: E1 | C5: Setling
A6: Mag&Sil | B6: E2 | C6: Mag&Sil
A7: Telcabo | B7: E3 | C7: Telcabo
A8: CAB_LIS01 | B8: V001 | C8: CAB_LIS01 72TB31
A9: CAB_LIS02 | B9: V002 | C9: CAB_LIS02 AV31FS
A10: CAB_LIS03 | B10: V003 | C10: CAB_LIS03 AT14CR
A11: CAB_LIS04 | B11: V004 | C11: CAB_LIS04 AN65DA
A12: CAB_LIS05 | B12: V005 | C12: CAB_LIS05 AV60FP
... A181: SV_LIS04 | B181: V223 | C181: SV_LIS04 22ZX01

Sheet Local Destino
A1: Localização de Destino
A2: Carrinha
A3: Devolução Armazém A
A4: Digi Porto

Sheet Novos Arm
A1: Armazém | B1: Descrição | C1: Armazém2 | D1: Matricula
A2: A | B2: Lisboa | C2: A
A3: AÇOR1 | B3: ILHA TERCEIRA | C3: AÇOR1
A4: AÇOR2 | B4: ILHA DO PICO | C4: AÇOR2
A5: AÇOR3 | B5: ILHA DO FAIAL | C5: AÇOR3
A6: AÇORE | B6: ILHA PONTA DELGADA | C6: AÇORE
A7: APE.A | B7: Apeados Lisboa | C7: APE.A
A8: APE.B | B8: Apeados Porto | C8: APE.B
A9: APE.C | B9: Apeados Leiria | C9: APE.C
A10: APE.D | B10: Apeados Faro | C10: APE.D
A11: APE.E | B11: Apeados Guarda | C11: APE.E
A12: APE.F | B12: Apeados Madeira | C12: APE.F
A13: APE.M | B13: Apeados Montalvo | C13: APE.M
... A40: V000 | B40: MERCADORIA TRANSITO | C40: V000
A41: V001 | B41: CAB_LIS01 | C41: V001 | D41: 72-TB-31
A42: V002 | B42: CAB_LIS02 | C42: V002 | D42: AV-31-FS
A43: V003 | B43: CAB_LIS03 | C43: V003 | D43: AT-14-CR
A44: V004 | B44: CAB_LIS04 | C44: V004 | D44: AN-65-DA
A45: V005 | B45: CAB_LIS05 | C45: V005 | D45: AV-60-FP
A46: V006 | B46: CAB_LIS06 | C46: V006 | D46: AS-54-VE
A47: V007 | B47: CAB_LIS07 | C47: V007 | D47: AS-60-VE
A48: V008 | B48: CAB_LIS08 | C48: V008 | D48: AS-01-VF
A49: V009 | B49: CAB_LIS09 | C49: V009 | D49: AT-63-AO
A50: V010 | B50: CAB_LIS10 | C50: V010 | D50: AT-55-DC
A51: V011 | B51: CAB_LIS11 | C51: V011 | D51: AT-71-DJ
A52: V012 | B52: CAB_LIS12 | C52: V012 | D52: BA-72-FV
... A57: V017 | B57: CAB_LIS17 | C57: V017 | D57: AT-77-NA
A58: V018 | B58: CAB_LIS18 | C58: V018
A59: V019 | B59: CAB_LIS19 | C59: V019 | D59: AO-36-UD
A60: V020 | B60: CAB_LIS20 | C60: V020 | D60: AQ-15-VS
A61: V021 | B61: CAB_LIS21 | C61: V021 | D61: AO-59-UD
A62: V022 | B62: CAB_LIS22 | C62: V022 | D62: AO-95-UD
A63: V023 | B63: CAB_POR01 | C63: V023 | D63: AT-77-NA
A64: V024 | B64: CAB_POR02 | C64: V024 | D64: AO-75-UD
A65: V025 | B65: CAB_POR03 | C65: V025 | D65: AO-19-UD
A66: V026 | B66: CAB_POR04 | C66: V026 | D66: AR-16-MH
A67: V027 | B67: CAB_POR05 | C67: V027 | D67: AT-91-LB
A68: V028 | B68: CAB_POR06 | C68: V028 | D68: AR-24-RJ
A69: V029 | B69: CAB_POR07 | C69: V029 | D69: AR-24-RJ
A70: V030 | B70: CAB_POR08 | C70: V030 | D70: AR-24-RJ
... A72: V032 | B72: CON_LIS01 | C72: V032 | D72: AU-75-JR
A73: V033 | B73: ENG_01 | C73: V033
A74: V034 | B74: CON_LIS03 | C74: V034
A75: V035 | B75: CON_LIS04 | C75: V035
A76: V036 | B76: ENG_02 | C76: V036
A77: V037 | B77: ENG_06 | C77: V037
A78: V038 | B78: CON_LIS07 | C78: V038
A79: V039 | B79: CON_LIS08 | C79: V039
A80: V040 | B80: CON_LIS09 | C80: V040
A81: V041 | B81: CON_LIS10 | C81: V041
A82: V042 | B82: CON_LIS11 | C82: V042
A83: V043 | B83: CON_LIS12 | C83: V043
A84: V044 | B84: CON_LIS13 | C84: V044
... A108: V068 | B108: CON_ROM10 | C108: V068
A109: V069 | B109: CON_ROM11 | C109: V069 | D109: AV-78-LU
A110: V070 | B110: CON_ROM12 | C110: V070
A111: V071 | B111: CON_ROM13 | C111: V071
A112: V072 | B112: CON_ROM14 | C112: V072
A113: V073 | B113: CON_ROM15 | C113: V073
A114: V074 | B114: CON_ROM16 | C114: V074
A115: V075 | B115: CON_ROM17 | C115: V075
A116: V076 | B116: CON_ROM18 | C116: V076
A117: V077 | B117: CON_ROM19 | C117: V077 | D117: AT-39-ET
A118: V078 | B118: CON_ROM20 | C118: V078 | D118: AV-33-PA
A119: V079 | B119: CON_ROM21 | C119: V079 | D119: B-858-RCS
A120: V080 | B120: CON_ROM22 | C120: V080
A121: V081 | B121: CON_ROM23 | C121: V081 | D121: B-519-TFN
A122: V082 | B122: CON_ROM24 | C122: V082
A123: V083 | B123: CON_ROM25 | C123: V083
A124: V084 | B124: CON_ROM26 | C124: V084
A125: V085 | B125: CON_ROM27 | C125: V085
A126: V086 | B126: CON_ROM28 | C126: V086
A127: V087 | B127: CON_ROM29 | C127: V087
A128: V088 | B128: CON_ROM30 | C128: V088 | D128: B-350-DGY
A129: V089 | B129: CON_ROM31 | C129: V089
A130: V090 | B130: CON_ROM32 | C130: V090
A131: V091 | B131: CON_ROM33 | C131: V091
A132: V092 | B132: CON_ROM34 | C132: V092
A133: V093 | B133: CON_ROM35 | C133: V093
A134: V094 | B134: CON_ROM36 | C134: V094 | D134: B-733-DGY
A135: V095 | B135: CON_ROM38 | C135: V095
A136: V096 | B136: CON_ROM39 | C136: V096
A137: V097 | B137: CON_ROM40 | C137: V097
A138: V098 | B138: CON_ROM41 | C138: V098 | D138: B-518-TFN
A139: V099 | B139: CON_ROM42 | C139: V099 | D139: AV-78-LU
A140: V100 | B140: CON_ROM43 | C140: V100 | D140: B-511-TFN
A141: V101 | B141: CON_ROM44 | C141: V101 | D141: B-513-TFN
A142: V102 | B142: CON_ROM45 | C142: V102 | D142: B-509-TFN
A143: V103 | B143: CON_ROM46 | C143: V103 | D143: B-506-TFN
A144: V104 | B144: CON_ROM47 | C144: V104 | D144: B-503-TFN
A145: V105 | B145: CON_ROM48 | C145: V105
A146: V106 | B146: CON_ROM49 | C146: V106
A147: V107 | B147: CON_ROM50 | C147: V107
A148: V108 | B148: CON_ROM51 | C148: V108
A149: V109 | B149: CON_ROM52 | C149: V109 | D149: AU-32-JS
A150: V110 | B150: CON_ROM53 | C150: V110
A151: V111 | B151: CON_ROM54 | C151: V111 | D151: BA-55-ER
A152: V112 | B152: CON_ROM56 | C152: V112 | D152: BA-32-ER
A153: V113 | B153: CON_ROM57 | C153: V113 | D153: AT-66-ET
A154: V114 | B154: CON_ROM58 | C154: V114
...
